{
        "configuration": {
            "validity_start": "2024-02-22T00:00:00Z",
            "validity_end": "2024-02-22T23:59:59Z",
            "timeZone": "CET"
        },
        "timeHorizon": {
            "Request_list": ["ID", "1D", "2D", "WK"]
        },
        "hours": [
            {
                "hour": "00:30",
                "priority": [
                    {"1": "PT0H"},
                    {"2": "PT1H"},
                    {"3": "PT2H"},
                    {"4": "PT3H"},
                    {"5": "PT4H"},
                    {"6": "PT5H"}
                ]
            },
            {
                "hour": "01:30",
                "priority": [
                    {"1": "PT0H"},
                    {"2": "PT1H"},
                    {"3": "PT2H"},
                    {"4": "PT3H"},
                    {"5": "-PT1H"},
                    {"6": "PT4H"}
                ]
            },
            {
                "hour": "02:30",
                "priority": [
                    {"1": "PT0H"},
                    {"2": "PT1H"},
                    {"3": "-PT1H"},
                    {"4": "PT2H"},
                    {"5": "-PT2H"},
                    {"6": "PT3H"}
                ]
            },
            {
                "hour": "03:30",
                "priority": [
                    {"1": "PT0H"},
                    {"2": "-PT1H"},
                    {"3": "PT1H"},
                    {"4": "-PT2H"},
                    {"5": "PT2H"},
                    {"6": "-PT3H"}
                ]
            },
            {
                "hour": "04:30",
                "priority": [
                    {"1": "PT0H"},
                    {"2": "-PT1H"},
                    {"3": "-PT2H"},
                    {"4": "-PT3H"},
                    {"5": "PT1H"},
                    {"6": "-PT4H"}
                ]
            },
            {
                "hour": "05:30",
                "priority": [
                    {"1": "PT0H"},
                    {"2": "-PT1H"},
                    {"3": "PT1H"},
                    {"4": "-PT2H"},
                    {"5": "-PT3H"}
                ]
            },
            {
                "hour": "06:30",
                "priority": [
                    {"1": "PT0H"},
                    {"2": "PT1H"},
                    {"3": "PT2H"},
                    {"4": "PT3H"},
                    {"5": "PT4H"},
                    {"6": "PT5H"},
                    {"7": "PT6H"}
                ]
            },
            {
                "hour": "07:30",
                "priority": [
                    {"1": "PT0H"},
                    {"2": "PT1H"},
                    {"3": "PT2H"},
                    {"4": "PT3H"},
                    {"5": "PT4H"},
                    {"6": "PT5H"}
                ]
            },
            {
                "hour": "08:30",
                "priority": [
                    {"1": "PT0H"},
                    {"2": "PT1H"},
                    {"3": "PT2H"},
                    {"4": "PT3H"},
                    {"5": "PT4H"}
                ]
            },
            {
                "hour": "09:30",
                "priority": [
                    {"1": "PT0H"},
                    {"2": "PT1H"},
                    {"3": "-PT1H"},
                    {"4": "PT2H"},
                    {"5": "PT3H"}
                ]
            },
            {
                "hour": "10:30",
                "priority": [
                    {"1": "PT0H"},
                    {"2": "-PT1H"},
                    {"3": "-PT2H"},
                    {"4": "PT1H"},
                    {"5": "PT2H"}
                ]
            },
            {
                "hour": "11:30",
                "priority": [
                    {"1": "PT0H"},
                    {"2": "-PT1H"},
                    {"3": "PT1H"},
                    {"4": "PT2H"},
                    {"5": "-PT2H"}
                ]
            },
            {
                "hour": "12:30",
                "priority": [
                    {"1": "PT0H"},
                    {"2": "-PT1H"},
                    {"3": "-PT2H"},
                    {"4": "PT1H"},
                    {"5": "-PT3H"}
                ]
            },
            {
                "hour": "13:30",
                "priority": [
                    {"1": "PT0H"},
                    {"2": "-PT1H"},
                    {"3": "PT1H"},
                    {"4": "-PT2H"},
                    {"5": "-PT3H"}
                ]
            },
            {
                "hour": "14:30",
                "priority": [
                    {"1": "PT0H"},
                    {"2": "PT1H"},
                    {"3": "PT2H"},
                    {"4": "-PT1H"},
                    {"5": "-PT2H"},
                    {"6": "-PT3H"},
                    {"7": "-PT4H"}
                ]
            },
            {
                "hour": "15:30",
                "priority": [
                    {"1": "PT0H"},
                    {"2": "PT1H"},
                    {"3": "PT2H"},
                    {"4": "-PT1H"},
                    {"5": "-PT2H"},
                    {"6": "-PT3H"}
                ]
            },
            {
                "hour": "16:30",
                "priority": [
                    {"1": "PT0H"},
                    {"2": "PT1H"},
                    {"3": "-PT1H"},
                    {"4": "-PT2H"},
                    {"5": "-PT3H"},
                    {"6": "-PT4H"}
                ]
            },
            {
                "hour": "17:30",
                "priority": [
                    {"1": "PT0H"},
                    {"2": "PT1H"},
                    {"3": "-PT1H"},
                    {"4": "-PT2H"},
                    {"5": "-PT3H"},
                    {"6": "-PT4H"},
                    {"7": "-PT5H"}
                ]
            },
            {
                "hour": "18:30",
                "priority": [
                    {"1": "PT0H"},
                    {"2": "-PT1H"},
                    {"3": "-PT2H"},
                    {"4": "-PT3H"},
                    {"5": "-PT4H"},
                    {"6": "-PT5H"},
                    {"7": "-PT6H"},
                    {"8": "PT1H"}

                ]
            },
            {
                "hour": "19:30",
                "priority": [
                    {"1": "PT0H"},
                    {"2": "PT1H"},
                    {"3": "-PT1H"},
                    {"4": "PT2H"},
                    {"5": "PT3H"}
                ]
            },
            {
                "hour": "20:30",
                "priority": [
                    {"1": "PT0H"},
                    {"2": "-PT1H"},
                    {"3": "PT1H"},
                    {"4": "PT2H"},
                    {"5": "PT3H"}
                ]
            },
            {
                "hour": "21:30",
                "priority": [
                    {"1": "PT0H"},
                    {"2": "-PT1H"},
                    {"3": "PT1H"},
                    {"4": "-PT2H"},
                    {"5": "PT2H"}
                ]
            },
            {
                "hour": "22:30",
                "priority": [
                    {"1": "PT0H"},
                    {"2": "-PT1H"},
                    {"3": "PT1H"},
                    {"4": "-PT2H"},
                    {"5": "-PT3H"}
                ]
            },
            {
                "hour": "23:30",
                "priority": [
                    {"1": "PT0H"},
                    {"2": "-PT1H"},
                    {"3": "-PT2H"},
                    {"4": "-PT3H"},
                    {"5": "-PT4H"}
                ]
            }
        ],
        "days": [
            {
                "day": 0,
                "priority": [
                    {"1": "P0D"},
                    {"2": "P1D"},
                    {"3": "-P7D"},
                    {"4": "-P6D"},
                    {"5": "-P5D"},
                    {"6": "-P4D"},
                    {"7": "-P3D"},
                    {"8": "-P14D"},
                    {"9": "-P13D"},
                    {"10": "-P12D"},
                    {"11": "-P11D"},
                    {"12": "-P10D"},
                    {"13": "-P2D"},
                    {"14": "-P1D"}
                ]
            },
            {
                "day": 1,
                "priority": [
                    {"1": "P0D"},
                    {"2": "P1D"},
                    {"3": "-P1D"},
                    {"4": "-P7D"},
                    {"5": "-P8D"},
                    {"6": "-P6D"},
                    {"7": "-P5D"},
                    {"8": "-P4D"},
                    {"9": "-P14D"},
                    {"10": "-P13D"},
                    {"11": "-P12D"},
                    {"12": "-P11D"},
                    {"13": "-P3D"},
                    {"14": "-P2D"}
                ]
            },
                        {
                "day": 2,
                "priority": [
                    {"1": "P0D"},
                    {"2": "P1D"},
                    {"3": "-P1D"},
                    {"4": "-P2D"},
                    {"5": "-P7D"},
                    {"6": "-P6D"},
                    {"7": "-P5D"},
                    {"8": "-P8D"},
                    {"9": "-P9D"},
                    {"10": "-P14D"},
                    {"11": "-P13D"},
                    {"12": "-P12D"},
                    {"13": "-P4D"},
                    {"14": "-P3D"}
                ]
            },
                        {
                "day": 3,
                "priority": [
                    {"1": "P0D"},
                    {"2": "-P1D"},
                    {"3": "P1D"},
                    {"4": "-P2D"},
                    {"5": "-P3D"},
                    {"6": "-P7D"},
                    {"7": "-P6D"},
                    {"8": "-P8D"},
                    {"9": "-P9D"},
                    {"10": "-P10D"},
                    {"11": "-P14D"},
                    {"12": "-P5D"},
                    {"13": "-P6D"},
                    {"14": "-P13D"}
                ]
            },
                        {
                "day": 4,
                "priority": [
                    {"1": "P0D"},
                    {"2": "-P1D"},
                    {"3": "-P2D"},
                    {"4": "-P3D"},
                    {"5": "-P4D"},
                    {"5": "-P7D"},
                    {"7": "-P8D"},
                    {"8": "-P9D"},
                    {"9": "-P10D"},
                    {"10": "-P11D"},
                    {"11": "-P14D"},
                    {"12": "-P6D"},
                    {"13": "-P13D"},
                    {"14": "-P5D"}
                ]
            },
                        {
                "day": 5,
                "priority": [
                    {"1": "P0D"},
                    {"2": "-P7D"},
                    {"3": "-P14D"},
                    {"4": "-P6D"},
                    {"5": "-P13D"},
                    {"6": "-P1D"},
                    {"7": "-P2D"},
                    {"8": "-P3D"},
                    {"9": "-P4D"},
                    {"10": "-P5D"},
                    {"11": "-P8D"},
                    {"12": "-P9D"},
                    {"13": "-P10D"},
                    {"14": "-P11D"}
                ]
            },
                        {
                "day": 6,
                "priority": [
                    {"1": "P0D"},
                    {"2": "-P7D"},
                    {"3": "-P14D"},
                    {"4": "-P1D"},
                    {"5": "-P8D"},
                    {"6": "-P3D"},
                    {"7": "-P4D"},
                    {"8": "-P5D"},
                    {"9": "-P6D"},
                    {"10": "-P9D"},
                    {"11": "-P10D"},
                    {"12": "-P11D"},
                    {"13": "-P12D"},
                    {"14": "-P13D"}
                ]
            }
        ]
    }